Metadata-Version: 2.1
Name: pathsaver
Version: 1.0
Summary: A Python script for saving, listing, and managing directory paths.
Home-page: https://github.com/TraXIcoN/pathsaver
Author: Aditya Mohan
Author-email: coding.traxicon16@gmail.com
License: MIT
Classifier: Programming Language :: Python :: 3
Classifier: License :: OSI Approved :: MIT License
Classifier: Operating System :: OS Independent
License-File: LICENSE
Requires-Dist: tabulate
Requires-Dist: argcomplete
